{
  "project_info": {
    "project_number": "445166218844",
    "firebase_url": "https://lovefoundit-4e54e-default-rtdb.europe-west1.firebasedatabase.app",
    "project_id": "lovefoundit-4e54e",
    "storage_bucket": "lovefoundit-4e54e.appspot.com"
  },
  "client": [
    {
      "client_info": {
        "mobilesdk_app_id": "1:445166218844:android:ba8f1a030eec4df4800099",
        "android_client_info": {
          "package_name": "com.lovefoundit.love_found_it"
        }
      },
      "oauth_client": [
        {
          "client_id": "445166218844-rcda23plu2bc1cb93ar5hsphodcpfha0.apps.googleusercontent.com",
          "client_type": 3
        }
      ],
      "api_key": [
        {
          "current_key": "AIzaSyA7hunrfRcQBP7ClfeuzLdYgoEfmwg71iU"
        }
      ],
      "services": {
        "appinvite_service": {
          "other_platform_oauth_client": [
            {
              "client_id": "445166218844-rcda23plu2bc1cb93ar5hsphodcpfha0.apps.googleusercontent.com",
              "client_type": 3
            },
            {
              "client_id": "445166218844-uuin2al6mknkdfc58ih1akd5rjlpq3q7.apps.googleusercontent.com",
              "client_type": 2,
              "ios_info": {
                "bundle_id": "com.lovefoundit.loveFoundIt"
              }
            }
          ]
        }
      }
    }
  ],
  "configuration_version": "1"
}